spelling_bee_game/__init__.py
spelling_bee_game-1.0.1.dist-info/METADATA
spelling_bee_game-1.0.1.dist-info/WHEEL
spelling_bee_game-1.0.1.dist-info/top_level.txt
spelling_bee_game-1.0.1.dist-info/RECORD
