Metadata-Version: 2.1
Name: spelling-bee-game
Version: 1.0.1
Summary: A simple spelling bee game
Home-page: UNKNOWN
Author: ChurningLava
Author-email: snoopydankl@gmail.com
License: UNKNOWN
Keywords: python,spelling-bee,game
Platform: UNKNOWN
Requires-Dist: opencv-python
Requires-Dist: beautifulsoup4
Requires-Dist: requests
